quads_mcp/__init__.py
quads_mcp/auth.py
quads_mcp/config.py
quads_mcp/server.py
quads_mcp/prompts/__init__.py
quads_mcp/prompts/quads_prompts.py
quads_mcp/resources/__init__.py
quads_mcp/resources/quads_resources.py
quads_mcp/tools/__init__.py
quads_mcp/tools/quads_tools.py
quads_mcp-0.1.0.dist-info/licenses/LICENSE
quads_mcp-0.1.0.dist-info/METADATA
quads_mcp-0.1.0.dist-info/WHEEL
quads_mcp-0.1.0.dist-info/entry_points.txt
quads_mcp-0.1.0.dist-info/top_level.txt
quads_mcp-0.1.0.dist-info/RECORD
