Metadata-Version: 2.4
Name: quads-mcp
Version: 0.1.0
Summary: A Model Context Protocol server for QUADS bare-metal server management
Author-email: Gonzalo Rafuls <grafuls@gmail.com>
License: MIT
Project-URL: Homepage, https://github.com/grafuls/quads-mcp
Project-URL: Repository, https://github.com/grafuls/quads-mcp
Project-URL: Bug Tracker, https://github.com/grafuls/quads-mcp/issues
Project-URL: Documentation, https://github.com/grafuls/quads-mcp/blob/main/README.md
Keywords: mcp,quads,server,management,bare-metal,claude
Classifier: Development Status :: 4 - Beta
Classifier: Intended Audience :: Developers
Classifier: Intended Audience :: System Administrators
Classifier: License :: OSI Approved :: MIT License
Classifier: Operating System :: OS Independent
Classifier: Programming Language :: Python :: 3
Classifier: Programming Language :: Python :: 3.12
Classifier: Topic :: System :: Systems Administration
Classifier: Topic :: Software Development :: Libraries :: Python Modules
Classifier: Topic :: Communications
Requires-Python: >=3.12
License-File: LICENSE
Requires-Dist: mcp>=1.0
Requires-Dist: httpx>=0.24.0
Requires-Dist: python-dotenv>=1.0.0
Provides-Extra: dev
Requires-Dist: pytest>=7.0; extra == "dev"
Requires-Dist: black>=23.0; extra == "dev"
Requires-Dist: isort>=5.0; extra == "dev"
Requires-Dist: mypy>=1.0; extra == "dev"
Requires-Dist: ruff>=0.2.0; extra == "dev"
Dynamic: license-file
